{
  "transactions": [
    {
      "id": 1,
      "description": "Desenvolvimento de site",
      "type": "income",
      "category": "Venda",
      "price": 14000,
      "createdAt": "2022-09-02T21:26:49.303Z"
    },
    {
      "id": 2,
      "description": "Monitor",
      "type": "outcome",
      "category": "Periféricos",
      "price": 2000,
      "createdAt": "2022-09-02T21:29:49.768Z"
    },
    {
      "id": 3,
      "description": "Cadeira",
      "type": "outcome",
      "category": "Periféricos",
      "price": 1190,
      "createdAt": "2022-09-02T23:23:23.768Z"
    },
    {
      "description": "Pastel",
      "price": 5,
      "category": "Alimentação",
      "type": "outcome",
      "createdAt": "2022-09-12T20:09:16.047Z",
      "id": 4
    }
  ]
}